[
	{
		"name": {
			"ru": "Равнины изобилия 45 ур.",
			"en": "googletranslate me plz"
		},
		"icon":
			"sparring_soul_shield",
		"obtaining": {
			"ru": "где татам",
			"en": "somewhere"
		},
		"pieces": {
			"health":  "#1810-3180 #1890-2500 #1980-2620 #2070-2740 #2240-2960 #2330-3080 #2410-3190 #2500-4390",
			"crit":    "    0-0      143-143      0-0        0-0        0-0       60-75       0-0        0-0   ",
			"acc":     "    0-0        0-0        0-0        0-0        0-0        0-0        0-0        0-0   ",
			"def":     "   46-58      48-61       0-0      156-156     57-72     176-176    182-182      0-0   ",
			"evade":   "    0-0        0-0        0-0       53-67     170-170      0-0       62-78      64-80  ",
			"block":   "   46-58       0-0      150-150      0-0        0-0        0-0       62-78      64-80  ",
			"critDef": "   46-58      48-61      51-150     53-156    170-170     60-75       0-0       64-80  ",
			"pierce":  "    0-0        0-0        0-0        0-0        0-0        0-0        0-0        0-0   ",
			"synth":   "   98-0      102-0      107-0      112-0      121-0      126-0      130-0      135-0   "
		},
		"bonus": {
			"health":  [0,1520,2130],
			"def":     [0,0,91],
			"block":   [50,0,0]
		}
	},
	{
		"name": {
			"ru": "По Хваран 45 ур.",
			"en": "..."
		},
		"icon":
			"blackram_supply_soul_shield",
		"obtaining": {
			"ru": "...",
			"en": "..."
		},
		"pieces": {
			"health":  "#1270-1810 #1330-1890 #1390-2620 #1450-2740 #1570-2240 #2860-4090 #1690-2410 #1750-3300",
			"crit":    "   46-58      48-61       0-0       53-67      57-72      60-75      62-78    #132-189 ",
			"acc":     "  #95-137   #100-143     51-64       0-0        0-0        0-0       62-78      64-80  ",
			"def":     "    0-0       48-61       0-0     #109-156     57-72      60-75      62-78      64-80  ",
			"evade":   "    0-0        0-0     #105-150      0-0     #119-170      0-0        0-0        0-0   ",
			"block":   "   46-58      48-61      51-64      53-67      57-72      60-75    #127-182      0-0   ",
			"critDef": "    0-0        0-0        0-0        0-0        0-0        0-0        0-0        0-0   ",
			"pierce":  "    0-0        0-0        0-0        0-0        0-0        0-0        0-0        0-0   ",
			"synth":   "   98-0      102-0      107-0      112-0      121-0      126-0      130-0      135-0   "
		},
		"bonus": {
			"acc":     [50,0,0],
			"evade":   [0,152,0],
			"block":   [0,0,91],
			"pierce":  [0,0,213]
		}
	},
	{
		"name": {
			"ru": "Хэ Мучина 45 ур.",
			"en": "..."
		},
		"icon":
			"bloodshade_soul_shield",
		"obtaining": {
			"ru": "...",
			"en": "..."
		},
		"pieces": {
			"health":  "#1700-2420 #2950-4220 #1860-2650 #1940-2770 #2100-3000 #2180-3120 #2260-3230 #2340-4290",
			"crit":    "   54-68      56-71      60-75      62-78    #139-199     70-88    #149-214   #149-221 ",
			"acc":     " #112-160     56-71      60-75      62-78      67-84    #144-206     72-91      75-94  ",
			"def":     "    0-0       56-71       0-0        0-0       67-84      70-88      72-91      74-94  ",
			"evade":   "   54-68       0-0       60-75    #128-183     67-84      70-88       0-0        0-0   ",
			"block":   "   54-68       0-0     #122-175     62-78       0-0        0-0       72-91       0-0   ",
			"critDef": "    0-0        0-0        0-0        0-0        0-0        0-0        0-0        0-0   ",
			"pierce":  "    0-0        0-0        0-0        0-0        0-0        0-0        0-0        0-0   ",
			"synth":   "  114-0      120-0      125-0      131-0      142-0      147-0      153-0      158-0   "
		},
		"bonus": {
			"acc":     [70,0,0],
			"evade":   [0,212,0],
			"block":   [0,0,117],
			"pierce":  [0,0,297]
		}
	}
]
